{"metadata": {"author": "JapanWeatherAssociation energy section", "title": "SYNFOS-solar 1km\u30e1\u30c3\u30b7\u30e5\u592a\u967d\u5149\u767a\u96fb\u51fa\u529b\u4e88\u6e2cAPI", "type": "http://api.jwa.or.jp", "parameter": {"latitude,longitude": "34.7037561598,137.3584203017", "date_and_time": "latest", "format": "json", "azimuth_angle": "180", "tilt_angle": "30", "rated_output_of_pv_array": null, "rated_output_of_pcs": null, "pv_array_installed_year": null}}, "results": [{"latitude": 34.7, "longitude": 137.3625, "initial_time": "2022-03-26T12:00:00Z", "azimuth_angle": 180.0, "tilt_angle": 30.0, "rated_output_of_pv_array": 100.0, "rated_output_of_pcs": 100.0, "pv_array_installed_year": 2022, "values": [{"forecast_time": "2022-03-26T12:30:00Z", "pv_output": {"value": 0}}, {"forecast_time": "2022-03-26T13:00:00Z", "pv_output": {"value": 0}}, {"forecast_time": "2022-03-26T13:30:00Z", "pv_output": {"value": 0}}, {"forecast_time": "2022-03-26T14:00:00Z", "pv_output": {"value": 0}}, {"forecast_time": "2022-03-26T14:30:00Z", "pv_output": {"value": 0}}, {"forecast_time": "2022-03-26T15:00:00Z", "pv_output": {"value": 0}}, {"forecast_time": "2022-03-26T15:30:00Z", "pv_output": {"value": 0}}, {"forecast_time": "2022-03-26T16:00:00Z", "pv_output": {"value": 0}}, {"forecast_time": "2022-03-26T16:30:00Z", "pv_output": {"value": 0}}, {"forecast_time": "2022-03-26T17:00:00Z", "pv_output": {"value": 0}}, {"forecast_time": "2022-03-26T17:30:00Z", "pv_output": {"value": 0}}, {"forecast_time": "2022-03-26T18:00:00Z", "pv_output": {"value": 0}}, {"forecast_time": "2022-03-26T18:30:00Z", "pv_output": {"value": 0}}, {"forecast_time": "2022-03-26T19:00:00Z", "pv_output": {"value": 0}}, {"forecast_time": "2022-03-26T19:30:00Z", "pv_output": {"value": 0}}, {"forecast_time": "2022-03-26T20:00:00Z", "pv_output": {"value": 0}}, {"forecast_time": "2022-03-26T20:30:00Z", "pv_output": {"value": 0}}, {"forecast_time": "2022-03-26T21:00:00Z", "pv_output": {"value": 0}}, {"forecast_time": "2022-03-26T21:30:00Z", "pv_output": {"value": 2.3029497476953553}}, {"forecast_time": "2022-03-26T22:00:00Z", "pv_output": {"value": 10.059614531783762}}, {"forecast_time": "2022-03-26T22:30:00Z", "pv_output": {"value": 18.909800808599275}}, {"forecast_time": "2022-03-26T23:00:00Z", "pv_output": {"value": 32.635789645284824}}, {"forecast_time": "2022-03-26T23:30:00Z", "pv_output": {"value": 42.90498533468988}}, {"forecast_time": "2022-03-27T00:00:00Z", "pv_output": {"value": 50.32200872753842}}, {"forecast_time": "2022-03-27T00:30:00Z", "pv_output": {"value": 57.71835968538032}}, {"forecast_time": "2022-03-27T01:00:00Z", "pv_output": {"value": 63.821443396017884}}, {"forecast_time": "2022-03-27T01:30:00Z", "pv_output": {"value": 69.87528607343604}}, {"forecast_time": "2022-03-27T02:00:00Z", "pv_output": {"value": 74.15155381682969}}, {"forecast_time": "2022-03-27T02:30:00Z", "pv_output": {"value": 76.36079929196994}}, {"forecast_time": "2022-03-27T03:00:00Z", "pv_output": {"value": 77.37016739758688}}, {"forecast_time": "2022-03-27T03:30:00Z", "pv_output": {"value": 77.29783576228162}}, {"forecast_time": "2022-03-27T04:00:00Z", "pv_output": {"value": 75.6407874549063}}, {"forecast_time": "2022-03-27T04:30:00Z", "pv_output": {"value": 72.86851566751952}}, {"forecast_time": "2022-03-27T05:00:00Z", "pv_output": {"value": 69.14164858434242}}, {"forecast_time": "2022-03-27T05:30:00Z", "pv_output": {"value": 63.87397910296119}}, {"forecast_time": "2022-03-27T06:00:00Z", "pv_output": {"value": 57.1682270317528}}, {"forecast_time": "2022-03-27T06:30:00Z", "pv_output": {"value": 49.23846092043637}}, {"forecast_time": "2022-03-27T07:00:00Z", "pv_output": {"value": 40.21209380450601}}, {"forecast_time": "2022-03-27T07:30:00Z", "pv_output": {"value": 30.373349939979974}}, {"forecast_time": "2022-03-27T08:00:00Z", "pv_output": {"value": 19.860308372943088}}, {"forecast_time": "2022-03-27T08:30:00Z", "pv_output": {"value": 9.265183135804879}}, {"forecast_time": "2022-03-27T09:00:00Z", "pv_output": {"value": 1.1796984481137929}}, {"forecast_time": "2022-03-27T09:30:00Z", "pv_output": {"value": 0}}, {"forecast_time": "2022-03-27T10:00:00Z", "pv_output": {"value": 0}}, {"forecast_time": "2022-03-27T10:30:00Z", "pv_output": {"value": 0}}, {"forecast_time": "2022-03-27T11:00:00Z", "pv_output": {"value": 0}}, {"forecast_time": "2022-03-27T11:30:00Z", "pv_output": {"value": 0}}, {"forecast_time": "2022-03-27T12:00:00Z", "pv_output": {"value": 0}}, {"forecast_time": "2022-03-27T12:30:00Z", "pv_output": {"value": 0}}, {"forecast_time": "2022-03-27T13:00:00Z", "pv_output": {"value": 0}}, {"forecast_time": "2022-03-27T13:30:00Z", "pv_output": {"value": 0}}, {"forecast_time": "2022-03-27T14:00:00Z", "pv_output": {"value": 0}}, {"forecast_time": "2022-03-27T14:30:00Z", "pv_output": {"value": 0}}, {"forecast_time": "2022-03-27T15:00:00Z", "pv_output": {"value": 0}}, {"forecast_time": "2022-03-27T15:30:00Z", "pv_output": {"value": 0}}, {"forecast_time": "2022-03-27T16:00:00Z", "pv_output": {"value": 0}}, {"forecast_time": "2022-03-27T16:30:00Z", "pv_output": {"value": 0}}, {"forecast_time": "2022-03-27T17:00:00Z", "pv_output": {"value": 0}}, {"forecast_time": "2022-03-27T17:30:00Z", "pv_output": {"value": 0}}, {"forecast_time": "2022-03-27T18:00:00Z", "pv_output": {"value": 0}}, {"forecast_time": "2022-03-27T18:30:00Z", "pv_output": {"value": 0}}, {"forecast_time": "2022-03-27T19:00:00Z", "pv_output": {"value": 0}}, {"forecast_time": "2022-03-27T19:30:00Z", "pv_output": {"value": 0}}, {"forecast_time": "2022-03-27T20:00:00Z", "pv_output": {"value": 0}}, {"forecast_time": "2022-03-27T20:30:00Z", "pv_output": {"value": 0}}, {"forecast_time": "2022-03-27T21:00:00Z", "pv_output": {"value": 0}}, {"forecast_time": "2022-03-27T21:30:00Z", "pv_output": {"value": 2.9926910181131143}}, {"forecast_time": "2022-03-27T22:00:00Z", "pv_output": {"value": 10.479762692724254}}, {"forecast_time": "2022-03-27T22:30:00Z", "pv_output": {"value": 20.60682890359112}}, {"forecast_time": "2022-03-27T23:00:00Z", "pv_output": {"value": 30.099756367046563}}, {"forecast_time": "2022-03-27T23:30:00Z", "pv_output": {"value": 38.755244796485364}}, {"forecast_time": "2022-03-28T00:00:00Z", "pv_output": {"value": 46.5703468708462}}, {"forecast_time": "2022-03-28T00:30:00Z", "pv_output": {"value": 52.82591662545191}}, {"forecast_time": "2022-03-28T01:00:00Z", "pv_output": {"value": 56.972063174177855}}, {"forecast_time": "2022-03-28T01:30:00Z", "pv_output": {"value": 61.7851814742851}}, {"forecast_time": "2022-03-28T02:00:00Z", "pv_output": {"value": 61.47206667403208}}, {"forecast_time": "2022-03-28T02:30:00Z", "pv_output": {"value": 62.23340593862754}}, {"forecast_time": "2022-03-28T03:00:00Z", "pv_output": {"value": 63.8219218008534}}, {"forecast_time": "2022-03-28T03:30:00Z", "pv_output": {"value": 60.741833038298765}}, {"forecast_time": "2022-03-28T04:00:00Z", "pv_output": {"value": 52.63728157152235}}, {"forecast_time": "2022-03-28T04:30:00Z", "pv_output": {"value": 48.37541531559212}}, {"forecast_time": "2022-03-28T05:00:00Z", "pv_output": {"value": 43.91527549897581}}, {"forecast_time": "2022-03-28T05:30:00Z", "pv_output": {"value": 39.73382534818381}}, {"forecast_time": "2022-03-28T06:00:00Z", "pv_output": {"value": 36.632458559513985}}, {"forecast_time": "2022-03-28T06:30:00Z", "pv_output": {"value": 30.19882186745428}}, {"forecast_time": "2022-03-28T07:00:00Z", "pv_output": {"value": 23.481894867234644}}, {"forecast_time": "2022-03-28T07:30:00Z", "pv_output": {"value": 17.980247335059847}}, {"forecast_time": "2022-03-28T08:00:00Z", "pv_output": {"value": 11.980148911459182}}, {"forecast_time": "2022-03-28T08:30:00Z", "pv_output": {"value": 5.665875141278124}}, {"forecast_time": "2022-03-28T09:00:00Z", "pv_output": {"value": 0.8411815129774997}}, {"forecast_time": "2022-03-28T09:30:00Z", "pv_output": {"value": 0}}, {"forecast_time": "2022-03-28T10:00:00Z", "pv_output": {"value": 0}}, {"forecast_time": "2022-03-28T10:30:00Z", "pv_output": {"value": 0}}, {"forecast_time": "2022-03-28T11:00:00Z", "pv_output": {"value": 0}}, {"forecast_time": "2022-03-28T11:30:00Z", "pv_output": {"value": 0}}, {"forecast_time": "2022-03-28T12:00:00Z", "pv_output": {"value": 0}}, {"forecast_time": "2022-03-28T12:30:00Z", "pv_output": {"value": 0}}, {"forecast_time": "2022-03-28T13:00:00Z", "pv_output": {"value": 0}}, {"forecast_time": "2022-03-28T13:30:00Z", "pv_output": {"value": 0}}, {"forecast_time": "2022-03-28T14:00:00Z", "pv_output": {"value": 0}}, {"forecast_time": "2022-03-28T14:30:00Z", "pv_output": {"value": 0}}, {"forecast_time": "2022-03-28T15:00:00Z", "pv_output": {"value": 0}}, {"forecast_time": "2022-03-28T15:30:00Z", "pv_output": {"value": 0}}, {"forecast_time": "2022-03-28T16:00:00Z", "pv_output": {"value": 0}}, {"forecast_time": "2022-03-28T16:30:00Z", "pv_output": {"value": 0}}, {"forecast_time": "2022-03-28T17:00:00Z", "pv_output": {"value": 0}}, {"forecast_time": "2022-03-28T17:30:00Z", "pv_output": {"value": 0}}, {"forecast_time": "2022-03-28T18:00:00Z", "pv_output": {"value": 0}}, {"forecast_time": "2022-03-28T18:30:00Z", "pv_output": {"value": 0}}, {"forecast_time": "2022-03-28T19:00:00Z", "pv_output": {"value": 0}}, {"forecast_time": "2022-03-28T19:30:00Z", "pv_output": {"value": 0}}, {"forecast_time": "2022-03-28T20:00:00Z", "pv_output": {"value": 0}}, {"forecast_time": "2022-03-28T20:30:00Z", "pv_output": {"value": 0}}, {"forecast_time": "2022-03-28T21:00:00Z", "pv_output": {"value": 0}}, {"forecast_time": "2022-03-28T21:30:00Z", "pv_output": {"value": 1.3503183418103812}}, {"forecast_time": "2022-03-28T22:00:00Z", "pv_output": {"value": 5.275467172006597}}, {"forecast_time": "2022-03-28T22:30:00Z", "pv_output": {"value": 9.079113422045134}}, {"forecast_time": "2022-03-28T23:00:00Z", "pv_output": {"value": 12.892963596284908}}, {"forecast_time": "2022-03-28T23:30:00Z", "pv_output": {"value": 15.791419059400575}}, {"forecast_time": "2022-03-29T00:00:00Z", "pv_output": {"value": 17.510897391906315}}, {"forecast_time": "2022-03-29T00:30:00Z", "pv_output": {"value": 17.633579755772903}}, {"forecast_time": "2022-03-29T01:00:00Z", "pv_output": {"value": 16.725985750993708}}, {"forecast_time": "2022-03-29T01:30:00Z", "pv_output": {"value": 17.162295449695034}}, {"forecast_time": "2022-03-29T02:00:00Z", "pv_output": {"value": 18.221514277691448}}, {"forecast_time": "2022-03-29T02:30:00Z", "pv_output": {"value": 21.310693155285755}}, {"forecast_time": "2022-03-29T03:00:00Z", "pv_output": {"value": 20.253721942137368}}, {"forecast_time": "2022-03-29T03:30:00Z", "pv_output": {"value": 20.51791378003337}}, {"forecast_time": "2022-03-29T04:00:00Z", "pv_output": {"value": 21.75298818431412}}, {"forecast_time": "2022-03-29T04:30:00Z", "pv_output": {"value": 18.66227585759707}}, {"forecast_time": "2022-03-29T05:00:00Z", "pv_output": {"value": 20.082425857641486}}, {"forecast_time": "2022-03-29T05:30:00Z", "pv_output": {"value": 15.579380532779016}}, {"forecast_time": "2022-03-29T06:00:00Z", "pv_output": {"value": 13.823609746765753}}, {"forecast_time": "2022-03-29T06:30:00Z", "pv_output": {"value": 12.161637997936355}}, {"forecast_time": "2022-03-29T07:00:00Z", "pv_output": {"value": 11.841336189896989}}, {"forecast_time": "2022-03-29T07:30:00Z", "pv_output": {"value": 9.121720243486786}}, {"forecast_time": "2022-03-29T08:00:00Z", "pv_output": {"value": 6.492592977816084}}, {"forecast_time": "2022-03-29T08:30:00Z", "pv_output": {"value": 2.990482316954204}}, {"forecast_time": "2022-03-29T09:00:00Z", "pv_output": {"value": 0.5111943258879525}}, {"forecast_time": "2022-03-29T09:30:00Z", "pv_output": {"value": 0}}, {"forecast_time": "2022-03-29T10:00:00Z", "pv_output": {"value": 0}}, {"forecast_time": "2022-03-29T10:30:00Z", "pv_output": {"value": 0}}, {"forecast_time": "2022-03-29T11:00:00Z", "pv_output": {"value": 0}}, {"forecast_time": "2022-03-29T11:30:00Z", "pv_output": {"value": 0}}, {"forecast_time": "2022-03-29T12:00:00Z", "pv_output": {"value": 0}}, {"forecast_time": "2022-03-29T12:30:00Z", "pv_output": {"value": 0}}, {"forecast_time": "2022-03-29T13:00:00Z", "pv_output": {"value": 0}}, {"forecast_time": "2022-03-29T13:30:00Z", "pv_output": {"value": 0}}, {"forecast_time": "2022-03-29T14:00:00Z", "pv_output": {"value": 0}}, {"forecast_time": "2022-03-29T14:30:00Z", "pv_output": {"value": 0}}, {"forecast_time": "2022-03-29T15:00:00Z", "pv_output": {"value": 0}}, {"forecast_time": "2022-03-29T15:30:00Z", "pv_output": {"value": 0}}, {"forecast_time": "2022-03-29T16:00:00Z", "pv_output": {"value": 0}}, {"forecast_time": "2022-03-29T16:30:00Z", "pv_output": {"value": 0}}, {"forecast_time": "2022-03-29T17:00:00Z", "pv_output": {"value": 0}}, {"forecast_time": "2022-03-29T17:30:00Z", "pv_output": {"value": 0}}, {"forecast_time": "2022-03-29T18:00:00Z", "pv_output": {"value": 0}}]}]}